[
    {
        "os_version": "BCLinux-for-Euler-21.10-dvd-aarch64-220620.iso",
        "osv_name": "中移（苏州）软件技术有限公司",
        "total_result": "pass",
        "type": "服务器",
        "date": "2022/12/2",
        "arch": "aarch64",
        "details": "详细信息",
        "friendly_link": "https://ecloud.10086.cn/",
        "os_download_link": "https://ecloud.10086.cn/",
        "checksum": "c4c92454d544177aff3a2aa4255cda44",
        "base_openeuler_version": "openEuler 20.03 LTS SP2",
        "tools_result": [
            {
                "name": "core_pkg",
                "percent": "NA",
                "result": "pass"
            },
            {
                "name": "soft_pkg",
                "percent": "NA",
                "result": "pass"
            },
            {
                "name": "KABI",
                "percent": "NA",
                "result": "pass"
            },
            {
                "name": "ABI",
                "percent": "NA",
                "result": "pass"
            },
            {
                "name": "service_config",
                "percent": "NA",
                "result": "pass"
            },
            {
                "name": "soft_config",
                "percent": "NA",
                "result": "pass"
            },
            {
                "name": "kernel_config",
                "percent": "NA",
                "result": "pass"
            }
        ],
        "platform_result": [
            {
                "name": "repo",
                "percent": "NA",
                "result": "pass"
            },
            {
                "name": "base_test",
                "percent": "NA",
                "result": "pass"
            },
            {
                "name": "performance_test",
                "percent": "NA",
                "result": "pass"
            },
            {
                "name": "running_config",
                "percent": "NA",
                "result": "pass"
            }
        ]
    },

    {
        "os_version": "EulerOS-V2.0SP10-aarch64-dvd.iso",
        "osv_name": "华为技术有限公司",
        "total_result": "pass",
        "type": "服务器",
        "date": "2022/12/2",
        "arch": "aarch64",
        "details": "详细信息",
        "friendly_link": "http://www.huawei.com/",
        "os_download_link": "http://www.huawei.com/",
        "checksum": "23b1ecb3fb0a9c793769ffdb9cf388f2",
        "base_openeuler_version": "openEuler 20.03 LTS SP1",
        "tools_result": [
            {
                "name": "core_pkg",
                "percent": "NA",
                "result": "pass"
            },
            {
                "name": "soft_pkg",
                "percent": "NA",
                "result": "pass"
            },
            {
                "name": "KABI",
                "percent": "NA",
                "result": "pass"
            },
            {
                "name": "ABI",
                "percent": "NA",
                "result": "pass"
            },
            {
                "name": "service_config",
                "percent": "NA",
                "result": "pass"
            },
            {
                "name": "soft_config",
                "percent": "NA",
                "result": "pass"
            },
            {
                "name": "kernel_config",
                "percent": "NA",
                "result": "pass"
            }
        ],
        "platform_result": [
            {
                "name": "repo",
                "percent": "NA",
                "result": "pass"
            },
            {
                "name": "base_test",
                "percent": "NA",
                "result": "pass"
            },
            {
                "name": "performance_test",
                "percent": "NA",
                "result": "pass"
            },
            {
                "name": "running_config",
                "percent": "NA",
                "result": "pass"
            }
        ]
    },

    {
        "os_version": "linxos-6.0-el20.03-sp3-arm64-DVD.iso",
        "osv_name": "北京凝思软件股份有限公司",
        "total_result": "pass",
        "type": "服务器",
        "date": "2022/12/2",
        "arch": "aarch64",
        "details": "详细信息",
        "friendly_link": "http://www.linx-info.com/",
        "os_download_link": "http://www.linx-info.com/",
        "checksum": "9fdeff087ec56100073ac6c572620570",
        "base_openeuler_version": "openEuler 20.03 LTS SP3",
        "tools_result": [
            {
                "name": "core_pkg",
                "percent": "NA",
                "result": "pass"
            },
            {
                "name": "soft_pkg",
                "percent": "NA",
                "result": "pass"
            },
            {
                "name": "KABI",
                "percent": "NA",
                "result": "pass"
            },
            {
                "name": "ABI",
                "percent": "NA",
                "result": "pass"
            },
            {
                "name": "service_config",
                "percent": "NA",
                "result": "pass"
            },
            {
                "name": "soft_config",
                "percent": "NA",
                "result": "pass"
            },
            {
                "name": "kernel_config",
                "percent": "NA",
                "result": "pass"
            }
        ],
        "platform_result": [
            {
                "name": "repo",
                "percent": "NA",
                "result": "pass"
            },
            {
                "name": "base_test",
                "percent": "NA",
                "result": "pass"
            },
            {
                "name": "performance_test",
                "percent": "NA",
                "result": "pass"
            },
            {
                "name": "running_config",
                "percent": "NA",
                "result": "pass"
            }
        ]
    },

    {
        "os_version": "linxos-6.0-el20.03-sp3-x86_64-DVD.iso",
        "osv_name": "北京凝思软件股份有限公司",
        "total_result": "pass",
        "type": "服务器",
        "date": "2022/12/2",
        "arch": "x86",
        "details": "详细信息",
        "friendly_link": "http://www.linx-info.com/",
        "os_download_link": "http://www.linx-info.com/",
        "checksum": "0a7d0e2cde9c6a014dee833345b03c64",
        "base_openeuler_version": "openEuler 20.03 LTS SP3",
        "tools_result": [
            {
                "name": "core_pkg",
                "percent": "NA",
                "result": "pass"
            },
            {
                "name": "soft_pkg",
                "percent": "NA",
                "result": "pass"
            },
            {
                "name": "KABI",
                "percent": "NA",
                "result": "pass"
            },
            {
                "name": "ABI",
                "percent": "NA",
                "result": "pass"
            },
            {
                "name": "service_config",
                "percent": "NA",
                "result": "pass"
            },
            {
                "name": "soft_config",
                "percent": "NA",
                "result": "pass"
            },
            {
                "name": "kernel_config",
                "percent": "NA",
                "result": "pass"
            }
        ],
        "platform_result": [
            {
                "name": "repo",
                "percent": "NA",
                "result": "pass"
            },
            {
                "name": "base_test",
                "percent": "NA",
                "result": "pass"
            },
            {
                "name": "performance_test",
                "percent": "NA",
                "result": "pass"
            },
            {
                "name": "running_config",
                "percent": "NA",
                "result": "pass"
            }
        ]
    },
    {
        "os_version": "ISSEL-22-LTS-x86_64-dvd.iso",
        "osv_name": "软通动力信息技术（集团）股份有限公司",
        "total_result": "pass",
        "type": "服务器",
        "date": "2022/12/2",
        "arch": "x86",
        "details": "详细信息",
        "friendly_link": "https://www.isoftstone.com/",
        "os_download_link": "https://www.isoftstone.com/",
        "checksum": "2aa7979fcd4a6551172ab937997892ca",
        "base_openeuler_version": "openEuler 22.03 LTS",
        "tools_result": [
            {
                "name": "core_pkg",
                "percent": "NA",
                "result": "pass"
            },
            {
                "name": "soft_pkg",
                "percent": "NA",
                "result": "pass"
            },
            {
                "name": "KABI",
                "percent": "NA",
                "result": "pass"
            },
            {
                "name": "ABI",
                "percent": "NA",
                "result": "pass"
            },
            {
                "name": "service_config",
                "percent": "NA",
                "result": "pass"
            },
            {
                "name": "soft_config",
                "percent": "NA",
                "result": "pass"
            },
            {
                "name": "kernel_config",
                "percent": "NA",
                "result": "pass"
            }
        ],
        "platform_result": [
            {
                "name": "repo",
                "percent": "NA",
                "result": "pass"
            },
            {
                "name": "base_test",
                "percent": "NA",
                "result": "pass"
            },
            {
                "name": "performance_test",
                "percent": "NA",
                "result": "pass"
            },
            {
                "name": "running_config",
                "percent": "NA",
                "result": "pass"
            }
        ]
    },

    {
        "os_version": "Kylin-Server-V10-SP3-General-Release-2211-ARM64.iso",
        "osv_name": "麒麟软件有限公司",
        "total_result": "pass",
        "type": "服务器",
        "date": "2022/12/2",
        "arch": "aarch64",
        "details": "详细信息",
        "friendly_link": "https://www.kylinos.cn",
        "os_download_link": "https://www.kylinos.cn",
        "checksum": "9c62d6277f7a1838539933508dc7b67e",
        "base_openeuler_version": "openEuler 20.03 LTS SP3",
        "tools_result": [
            {
                "name": "core_pkg",
                "percent": "NA",
                "result": "pass"
            },
            {
                "name": "soft_pkg",
                "percent": "NA",
                "result": "pass"
            },
            {
                "name": "KABI",
                "percent": "NA",
                "result": "pass"
            },
            {
                "name": "ABI",
                "percent": "NA",
                "result": "pass"
            },
            {
                "name": "service_config",
                "percent": "NA",
                "result": "pass"
            },
            {
                "name": "soft_config",
                "percent": "NA",
                "result": "pass"
            },
            {
                "name": "kernel_config",
                "percent": "NA",
                "result": "pass"
            }
        ],
        "platform_result": [
            {
                "name": "repo",
                "percent": "NA",
                "result": "pass"
            },
            {
                "name": "base_test",
                "percent": "NA",
                "result": "pass"
            },
            {
                "name": "performance_test",
                "percent": "NA",
                "result": "pass"
            },
            {
                "name": "running_config",
                "percent": "NA",
                "result": "pass"
            }
        ]
    },

    {
        "os_version": "Kylin-Server-V10-SP3-General-Release-2211-X86_64.iso",
        "osv_name": "麒麟软件有限公司",
        "total_result": "pass",
        "type": "服务器",
        "date": "2022/12/2",
        "arch": "X86",
        "details": "详细信息",
        "friendly_link": "https://www.kylinos.cn",
        "os_download_link": "https://www.kylinos.cn",
        "checksum": "597617fb66b44d9ecb1ae9d0612ee34a",
        "base_openeuler_version": "openEuler 20.03 LTS SP3",
        "tools_result": [
            {
                "name": "core_pkg",
                "percent": "NA",
                "result": "pass"
            },
            {
                "name": "soft_pkg",
                "percent": "NA",
                "result": "pass"
            },
            {
                "name": "KABI",
                "percent": "NA",
                "result": "pass"
            },
            {
                "name": "ABI",
                "percent": "NA",
                "result": "pass"
            },
            {
                "name": "service_config",
                "percent": "NA",
                "result": "pass"
            },
            {
                "name": "soft_config",
                "percent": "NA",
                "result": "pass"
            },
            {
                "name": "kernel_config",
                "percent": "NA",
                "result": "pass"
            }
        ],
        "platform_result": [
            {
                "name": "repo",
                "percent": "NA",
                "result": "pass"
            },
            {
                "name": "base_test",
                "percent": "NA",
                "result": "pass"
            },
            {
                "name": "performance_test",
                "percent": "NA",
                "result": "pass"
            },
            {
                "name": "running_config",
                "percent": "NA",
                "result": "pass"
            }
        ]
    }

]